{"dimmed":{"inactive":"#23223d","subtle":"#565393"},"scheme-name":"amora","diagnostic":{"info":"#adcfbc","error":"#e83f80","warn":"#f79f79","hint":"#93c5e6"},"cyan":"#a2baa8","fg":"#dedbeb","magenta":"#9985d1","built_in":{"function":"#a29dff","keyword":"#fb5c8e","type":"#f7d98d","constant":"#b4a4de","variable":"#93c5e6"},"bg":{"alt":"#2c223c","selected":"#2c223c","base":"#1a1a2e"},"search_result":{"bg":"#e83f80","fg":"#1a1a2e","telescope":"#ed86ea"},"syntax":{"number":"#b4a4de","punctuation":"#e68ac1","tag":"#aed9f6","struct":"#f6e08b","constant":"#b4a4de","operator":"#e68ac1","statement":"#f09eed","keyword":"#ed3f7f","comment":"#565393","string":"#9fd3b3","parameter":"#f79f79","include":"#fb5c8e","field":"#ff9f50","conditional":"#df8b92","function":"#a29dff","property":"#b2aeff","identifier":"#84c49b","todo":{"fg":"#dedbeb","bg":"#e83f80"},"type":"#93c5e6","constructor":"#ed86ea","preproc":"#ffb65e","variable":"#dedbeb"},"heading":{"h1":"#9985d1","h2":"#b4a4de"},"diff":{"change":"#ea6634","text":"#b3dfef","remove":"#e83f80","add":"#adcfbc"},"uri":"#84c49b","orange":"#ea6634","pum":{"bg":"#565393","thumb":"#b3dfef","sbar":"#313a43","fg":"#dedbeb","sel":{"bg":"#a29dff","fg":"#161627"}},"red":"#e83f80","inc_search":{"fg":"#1a1a2e","bg":"#e83f80"},"border":"#b4a4de","yellow":"#f7d98d","blue":"#bdceed","match":"#6c8391","accent":"#f09eed","directory":"#df8b92","green":"#adcfbc"}