{"green":"#adcfbc","orange":"#ea6634","diff":{"remove":"#e83f80","change":"#ea6634","add":"#adcfbc","text":"#b3dfef"},"diagnostic":{"hint":"#93c5e6","warn":"#f79f79","error":"#e83f80","info":"#adcfbc"},"blue":"#bdceed","directory":"#df8b92","red":"#e83f80","uri":"#84c49b","dimmed":{"subtle":"#565393","inactive":"#23223d"},"magenta":"#9985d1","built_in":{"keyword":"#fb5c8e","type":"#f7d98d","function":"#a29dff","constant":"#b4a4de","variable":"#93c5e6"},"inc_search":{"fg":"#1a1a2e","bg":"#e83f80"},"scheme-name":"amora","border":"#b4a4de","pum":{"fg":"#dedbeb","thumb":"#b3dfef","bg":"#565393","sel":{"bg":"#a29dff","fg":"#161627"},"sbar":"#313a43"},"syntax":{"operator":"#e68ac1","punctuation":"#e68ac1","type":"#93c5e6","comment":"#565393","variable":"#dedbeb","include":"#fb5c8e","tag":"#aed9f6","preproc":"#ffb65e","constant":"#b4a4de","property":"#b2aeff","struct":"#f6e08b","keyword":"#ed3f7f","conditional":"#df8b92","function":"#a29dff","number":"#b4a4de","todo":{"fg":"#dedbeb","bg":"#e83f80"},"identifier":"#84c49b","parameter":"#f79f79","field":"#ff9f50","statement":"#f09eed","constructor":"#ed86ea","string":"#9fd3b3"},"heading":{"h1":"#9985d1","h2":"#b4a4de"},"cyan":"#a2baa8","bg":{"selected":"#2c223c","alt":"#2c223c","base":"#1a1a2e"},"match":"#6c8391","search_result":{"fg":"#1a1a2e","telescope":"#ed86ea","bg":"#e83f80"},"accent":"#f09eed","yellow":"#f7d98d","fg":"#dedbeb"}