{"magenta":"#A37ACC","yellow":"#FF6A00","accent":"#e6b673","syntax":{"type":"#36a3d9","constant":"#a37acc","include":"#e6b673","operator":"#e7c547","field":"#36a3d9","preproc":"#e6b673","number":"#a37acc","constructor":"#e6b673","property":"#36a3d9","function":"#f29718","comment":"#abb0b6","keyword":"#ff7733","parameter":"#36a3d9","struct":"#e6b673","punctuation":"#e6b673","string":"#86b300","todo":{"bg":"#0","fg":"#f07178"},"conditional":"#ff7733","statement":"#ff7733","variable":"#0","tag":"#ff7733"},"diff":{"add":"#ffffff","text":"#ffffff","change":"#ffffff","remove":"#8b8b"},"pum":{"sbar":"#808080","thumb":"#ffffff","bg":"#f0eee4","sel":{"bg":"#f0eee4","fg":"#5c6773"},"fg":"#5c6773"},"cursorlinenr":"#ff6a00","green":"#86B300","scheme-name":"ayu","border":"#fafafa","search_result":{"bg":"#a37acc","telescope":"#0","fg":"#fafafa"},"bg":{"selected":"#f3f3f3","alt":"#f0eee4","base":"#fafafa"},"dimmed":{"subtle":"#828c99","inactive":"#d9d8d7"},"fg":"#5c6773","inc_search":{"bg":"#0","fg":"#0"},"diagnostic":{"info":"#add8e6","hint":"#d3d3d3","error":"#ff0000","warn":"#ffa500"},"match":"#0","blue":"#36A3D9","uri":"#36a3d9","cyan":"#4CBF99","heading":{"h1":"#0","h2":"#0"},"built_in":{"type":"#36a3d9","constant":"#e6b673","function":"#e6b673","variable":"#e6b673","keyword":"#ff7733"},"orange":"#FF6A00"}