{"yellow":"#FFCC66","fg":"#d9d7ce","diagnostic":{"info":"#add8e6","error":"#ff0000","hint":"#d3d3d3","warn":"#ffa500"},"dimmed":{"inactive":"#3d4751","subtle":"#607080"},"cursorlinenr":"#ffcc66","cyan":"#95E6CB","border":"#212733","match":"#0","green":"#BBE67E","accent":"#ffc44c","syntax":{"constant":"#d4bfff","conditional":"#ffae57","preproc":"#ffc44c","variable":"#0","comment":"#5c6773","todo":{"fg":"#f07178","bg":"#0"},"include":"#ffc44c","struct":"#ffc44c","string":"#bbe67e","constructor":"#ffc44c","function":"#ffd57f","number":"#d4bfff","punctuation":"#ffc44c","property":"#5ccfe6","type":"#5ccfe6","parameter":"#5ccfe6","statement":"#ffae57","keyword":"#ffae57","operator":"#80d4ff","field":"#5ccfe6","tag":"#ffae57"},"scheme-name":"ayu_mirage","inc_search":{"bg":"#0","fg":"#0"},"search_result":{"telescope":"#0","fg":"#212733","bg":"#d4bfff"},"blue":"#5CCFE6","pum":{"fg":"#d9d7ce","thumb":"#ffffff","sbar":"#808080","sel":{"bg":"#343f4c","fg":"#d9d7ce"},"bg":"#343f4c"},"orange":"#FFCC66","diff":{"remove":"#8b8b","text":"#272d38","add":"#272d38","change":"#272d38"},"heading":{"h2":"#0","h1":"#0"},"magenta":"#D4BFFF","built_in":{"keyword":"#ffae57","type":"#5ccfe6","function":"#ffc44c","variable":"#ffc44c","constant":"#ffc44c"},"bg":{"selected":"#242b38","alt":"#343f4c","base":"#212733"},"uri":"#5ccfe6"}