{"green":"#A3BE8C","cursorlinenr":"#625566","blue":"#61afef","fg":"#e1d9ea","inc_search":{"bg":"#60d0d","fg":"#63b0b0"},"search_result":{"fg":"#0","bg":"#202727","telescope":"#654a96"},"border":"#222827","pum":{"bg":"#120f12","sbar":"#222827","fg":"#9c75dd","thumb":"#9898ae","sel":{"bg":"#0","fg":"#0"}},"orange":"#e7c787","uri":"#e4dcec","cyan":"#519ABA","diff":{"change":"#5786bc","add":"#63b0b0","remove":"#cd749c","text":"#9898ae"},"magenta":"#c882e7","dimmed":{"inactive":"#29292e","subtle":"#654a96"},"scheme-name":"boo","bg":{"alt":"#d0d0d","base":"#131316","selected":"#222827"},"accent":"#654a96","syntax":{"property":"#738d8d","constant":"#7d6c82","number":"#d9d6cf","field":"#5d6f74","variable":"#a7d3d3","constructor":"#63b0b0","include":"#63b0b0","struct":"#63b0b0","operator":"#656568","punctuation":"#4b4b4e","type":"#63b0b0","string":"#72d4d4","statement":"#63b0b0","tag":"#85c1c1","keyword":"#5c4489","comment":"#9898ae","preproc":"#63b0b0","function":"#6eacb8","parameter":"#a9d1df","conditional":"#53757e","todo":{"fg":"#3f3442","bg":"#0"}},"match":"#0","built_in":{"variable":"#32547b","function":"#748a90","type":"#3a7272","constant":"#4291ad","keyword":"#654a96"},"diagnostic":{"error":"#c988df","info":"#e4dcec","warn":"#a9d1df","hint":"#5d4663"},"heading":{"h1":"#0","h2":"#0"},"yellow":"#e7c787"}