{"diff":{"add":"#69ff94","text":"#BD93F9","remove":"#E95678","change":"#F1FA8C"},"dimmed":{"inactive":"#6272a4","subtle":"#666771"},"bg":{"selected":"#44475a","base":"#282a36","alt":"#232531"},"heading":{"h2":"#BD93F9","h1":"#BD93F9"},"orange":"#FFB86C","blue":"#BD93F9","fg":"#F8F8F2","pum":{"fg":"#6272a4","sel":{"fg":"#e9e9f4","bg":"#b389ef"},"bg":"#373844","thumb":"#b389ef","sbar":"#44475a"},"green":"#69ff94","yellow":"#F1FA8C","uri":"#ffb86c","magenta":"#BD93F9","cyan":"#0088cc","inc_search":{"bg":"#bd93f9","fg":"#3a3c4e"},"scheme-name":"dracula","syntax":{"punctuation":"#f7f7fb","number":"#bd93f9","function":"#69ff94","variable":"#e9e9f4","parameter":"#ffb86c","conditional":"#ff92df","type":"#8be9fd","comment":"#6272a4","keyword":"#ff92df","struct":"#ff92df","operator":"#e9e9f4","constant":"#bd93f9","string":"#ffffa5","statement":"#ffb86c","property":"#ffb86c","constructor":"#8be9fd","field":"#8be9fd","include":"#69ff94","preproc":"#8be9fd","identifier":"#ffb86c","todo":{"bg":"#3a3c4e","fg":"#8be9fd"}},"built_in":{"type":"#8be9fd","keyword":"#ff92df","constant":"#bd93f9","function":"#8be9fd","variable":"#8be9fd"},"diagnostic":{"hint":"#BD93F9","error":"#E95678","info":"#69ff94","warn":"#F1FA8C"},"red":"#E95678","match":"#6272a4","border":"#BD93F9","directory":"#BD93F9","search_result":{"fg":"#3a3c4e","bg":"#8be9fd","telescope":"#8be9fd"},"accent":"#8be9fd"}