{"match":"#e9e8d2","border":"#7393b3","accent":"#e69875","uri":"#7fbbb3","magenta":"#d699b6","orange":"#e69875","cyan":"#69a59d","bg":{"alt":"#272f35","base":"#2b3339","selected":"#3a4248"},"dimmed":{"inactive":"#868d80","subtle":"#50585e"},"fg":"#D3C6AA","scheme-name":"everforest","heading":{"h1":"#7393b3","h2":"#7393b3"},"pum":{"fg":"#e9e8d2","bg":"#333b41","sel":{"bg":"#83c092","fg":"#d3c6aa"},"thumb":"#78b4ac","sbar":"#363e44"},"blue":"#7393b3","yellow":"#dbbc7f","inc_search":{"fg":"#323c41","bg":"#d699b6"},"directory":"#7393b3","diagnostic":{"info":"#83c092","warn":"#dbbc7f","error":"#e67e80","hint":"#b4bbc8"},"red":"#e67e80","search_result":{"fg":"#323c41","telescope":"#83c092","bg":"#83c092"},"syntax":{"string":"#dbbc7f","comment":"#868d80","punctuation":"#d699b6","statement":"#7fbbb3","keyword":"#e67e80","number":"#d699b6","parameter":"#7fbbb3","constructor":"#e69875","include":"#a7c080","type":"#83c092","preproc":"#83c092","function":"#a7c080","operator":"#d3c6aa","struct":"#e67e80","conditional":"#e67e80","property":"#7fbbb3","constant":"#d699b6","todo":{"fg":"#83c092","bg":"#323c41"},"field":"#83c092","identifier":"#7fbbb3","variable":"#d3c6aa"},"green":"#83c092","diff":{"change":"#dbbc7f","add":"#83c092","text":"#7393b3","remove":"#e67e80"},"built_in":{"keyword":"#e67e80","constant":"#d699b6","type":"#83c092","function":"#e69875","variable":"#e69875"}}