{"diagnostic":{"hint":"#b4bbc8","info":"#83c092","warn":"#dbbc7f","error":"#e67e80"},"bg":{"alt":"#272f35","selected":"#3a4248","base":"#2b3339"},"blue":"#7393b3","yellow":"#dbbc7f","uri":"#7fbbb3","heading":{"h1":"#7393b3","h2":"#7393b3"},"magenta":"#d699b6","accent":"#e69875","search_result":{"fg":"#323c41","telescope":"#83c092","bg":"#83c092"},"syntax":{"comment":"#868d80","string":"#dbbc7f","constant":"#d699b6","constructor":"#e69875","operator":"#d3c6aa","property":"#7fbbb3","function":"#a7c080","number":"#d699b6","parameter":"#7fbbb3","statement":"#7fbbb3","punctuation":"#d699b6","struct":"#e67e80","conditional":"#e67e80","type":"#83c092","todo":{"fg":"#83c092","bg":"#323c41"},"variable":"#d3c6aa","field":"#83c092","identifier":"#7fbbb3","preproc":"#83c092","include":"#a7c080","keyword":"#e67e80"},"inc_search":{"fg":"#323c41","bg":"#d699b6"},"red":"#e67e80","built_in":{"constant":"#d699b6","variable":"#e69875","type":"#83c092","function":"#e69875","keyword":"#e67e80"},"scheme-name":"everforest","directory":"#7393b3","pum":{"fg":"#e9e8d2","thumb":"#78b4ac","sbar":"#363e44","bg":"#333b41","sel":{"bg":"#83c092","fg":"#d3c6aa"}},"cyan":"#69a59d","green":"#83c092","border":"#7393b3","match":"#e9e8d2","dimmed":{"subtle":"#50585e","inactive":"#868d80"},"diff":{"add":"#83c092","text":"#7393b3","remove":"#e67e80","change":"#dbbc7f"},"fg":"#D3C6AA","orange":"#e69875"}