{"yellow":"#d29922","magenta":"#bc8cff","bg":{"alt":"#d1117","base":"#d1117","selected":"#161b22"},"blue":"#58a6ff","cyan":"#39c5cf","uri":"#0","syntax":{"type":"#d69a00","preproc":"#d69a00","todo":{"bg":"#d29922","fg":"#d1117"},"variable":"#9b4215","struct":"#d69a00","keyword":"#d69a00","parameter":"#c9d1d9","number":"#79b8ff","function":"#d2a8ff","property":"#d2a8ff","punctuation":"#c9d1d9","constant":"#79b8ff","include":"#d69a00","tag":"#83d4ff","field":"#c9d1d9","statement":"#d69a00","conditional":"#d69a00","string":"#a5d6ff","operator":"#d69a00","constructor":"#9b4215","comment":"#8b949e"},"accent":"#9b4215","search_result":{"bg":"#2c2b1c","telescope":"#79b8ff","fg":"#0"},"fg":"#c9d1d9","match":"#58a6ff","border":"#b3b1ad","orange":"#e3b341","dimmed":{"inactive":"#d1117","subtle":"#d1117"},"heading":{"h1":"#0","h2":"#0"},"green":"#3fb950","inc_search":{"bg":"#2c2b1c","fg":"#0"},"pum":{"bg":"#161b22","sel":{"bg":"#5e94c5","fg":"#161b22"},"thumb":"#31373d","fg":"#c9d1d9","sbar":"#161b22"},"diff":{"remove":"#462c32","text":"#0","add":"#244032","change":"#341a00"},"scheme-name":"github_dark_colorblind","built_in":{"type":"#d69a00","variable":"#9b4215","keyword":"#d69a00","function":"#9b4215","constant":"#9b4215"},"cursorlinenr":"#c9d1d9","diagnostic":{"error":"#f85149","hint":"#eeeeb3","info":"#75beff","warn":"#f0883e"}}