{"fg":"#24292f","syntax":{"punctuation":"#24292f","constructor":"#5cc5","comment":"#6a737d","include":"#d73a49","variable":"#5cc5","tag":"#22863a","conditional":"#d73a49","constant":"#5cc5","property":"#6f42c1","field":"#24292f","keyword":"#d73a49","string":"#32f62","number":"#5cc5","preproc":"#d73a49","function":"#6f42c1","type":"#d73a49","statement":"#d73a49","todo":{"bg":"#dbab09","fg":"#ffffff"},"struct":"#d73a49","parameter":"#24292e","operator":"#d73a49"},"scheme-name":"github_light","bg":{"base":"#ffffff","selected":"#d5e5f6","alt":"#ffffff"},"uri":"#0","cursorlinenr":"#24292e","pum":{"fg":"#24292f","thumb":"#f0f1f3","sel":{"bg":"#4085d4","fg":"#f6f8fa"},"bg":"#f6f8fa","sbar":"#f6f8fa"},"match":"#366d6","blue":"#0366d6","cyan":"#0598bc","diagnostic":{"error":"#cb2431","hint":"#6c6c6c","warn":"#bf8803","info":"#75beff"},"dimmed":{"inactive":"#ffffff","subtle":"#ffffff"},"diff":{"remove":"#fae5e7","text":"#0","add":"#d4f8db","change":"#fff5b1"},"inc_search":{"bg":"#fff2be","fg":"#0"},"magenta":"#5a32a3","built_in":{"variable":"#5cc5","type":"#d73a49","function":"#5cc5","keyword":"#d73a49","constant":"#5cc5"},"green":"#28a745","yellow":"#dbab09","orange":"#b08800","border":"#44289","heading":{"h1":"#0","h2":"#0"},"accent":"#5cc5","search_result":{"bg":"#fff2be","telescope":"#5cc5","fg":"#0"}}