{"cyan":"#39c5cf","built_in":{"variable":"#9b4215","type":"#d69a00","keyword":"#d69a00","function":"#9b4215","constant":"#9b4215"},"pum":{"sel":{"fg":"#161b22","bg":"#5e94c5"},"bg":"#161b22","thumb":"#31373d","sbar":"#161b22","fg":"#c9d1d9"},"yellow":"#d29922","diff":{"change":"#341a00","text":"#0","remove":"#462c32","add":"#244032"},"heading":{"h1":"#0","h2":"#0"},"uri":"#0","accent":"#9b4215","scheme-name":"github_dark_colorblind","dimmed":{"subtle":"#d1117","inactive":"#d1117"},"bg":{"base":"#d1117","alt":"#d1117","selected":"#161b22"},"cursorlinenr":"#c9d1d9","green":"#3fb950","search_result":{"bg":"#2c2b1c","fg":"#0","telescope":"#79b8ff"},"fg":"#c9d1d9","orange":"#e3b341","inc_search":{"fg":"#0","bg":"#2c2b1c"},"match":"#58a6ff","diagnostic":{"error":"#f85149","hint":"#eeeeb3","info":"#75beff","warn":"#f0883e"},"magenta":"#bc8cff","syntax":{"constructor":"#9b4215","parameter":"#c9d1d9","operator":"#d69a00","tag":"#83d4ff","keyword":"#d69a00","number":"#79b8ff","string":"#a5d6ff","type":"#d69a00","struct":"#d69a00","include":"#d69a00","preproc":"#d69a00","todo":{"fg":"#d1117","bg":"#d29922"},"constant":"#79b8ff","statement":"#d69a00","variable":"#9b4215","punctuation":"#c9d1d9","comment":"#8b949e","field":"#c9d1d9","function":"#d2a8ff","conditional":"#d69a00","property":"#d2a8ff"},"border":"#b3b1ad","blue":"#58a6ff"}