{"remaps":{"plugins":{"telescope":{"TelescopeResultsNormal":{"bg":"#1a181b"},"TelescopePreviewNormal":{"bg":"#1a181b"},"TelescopeSelectionCaret":{"bg":"#1a181b","fg":"#661fad"},"TelescopeMatching":{"bg":"#8f9fef"},"TelescopePromptBorder":{"bg":"#1a181b","fg":"#e9e2e9"},"TelescopeSelection":{"bg":"#343036"},"TelescopePromptNormal":{"bg":"#1a181b","fg":"#e9e2e9"},"TelescopePromptTitle":{"bg":"#ffff80","fg":"#1a181b"},"TelescopeBorder":{"bg":"#1a181b","fg":"#1a181b"},"TelescopeResultsTitle":{"bg":"#4c66e6","fg":"#1a181b"},"TelescopePreviewTitle":{"bg":"#8fef97","fg":"#1a181b"},"TelescopePromptPrefix":{"fg":"#ff9933"},"TelescopePromptCounter":{"fg":"#9500ff"}},"cmp":{"CmpItemAbbrMatchFuzzy":{"fg":"#9500ff"},"CmpItemAbbrMatch":{"fg":"#9500ff"},"CmpItemMenu":{"fg":"#4ce659"},"CmpItemAbbrDeprecated":{"fg":"#ff3333"}}}},"bg":{"base":"#272428","alt":"#1a181b","selected":"#343036"},"dimmed":{"inactive":"#343036","subtle":"#343036"},"blue":"#4c66e6","fg":"#e9e2e9","built_in":{"function":"#8f9fef","keyword":"#ff8080","constant":"#ffff80","variable":"#ff8080"},"green":"#4ce659","inc_search":{"bg":"#ca80ff","fg":"#f4f0f4"},"scheme-name":"kurai","red":"#ff3333","yellow":"#ffff80","heading":{"h1":"#8fef97","h2":"#4ce659"},"pum":{"bg":"#1a181b","sel":{"fg":"#e9e2e9","bg":"#272428"},"thumb":"#e9e2e9","sbar":"#272428","fg":"#e9e2e9"},"magenta":"#9500ff","diagnostic":{"hint":"#4c66e6","info":"#9500ff","warn":"#ffff33","error":"#ff3333"},"syntax":{"include":"#ffbf80","keyword":"#ca80ff","number":"#ff8080","parameter":"#ca80ff","variable":"#e9e2e9","todo":{"bg":"#aa33ff","fg":"#f4f0f4"},"constructor":"#7f20df","function":"#8f9fef","statement":"#ca80ff","field":"#8f9fef","string":"#ffff80","constant":"#ffff33","punctuation":"#68616b","property":"#4c66e6","type":"#8fef97","struct":"#4c66e6","comment":"#68616b","operator":"#ca80ff","preproc":"#ffff80","conditional":"#ca80ff"},"search_result":{"telescope":"#e9e2e9","bg":"#8f9fef","fg":"#e9e2e9"},"orange":"#ff9933","diff":{"text":"#8f9fef","delete":"#ff3333","change":"#ffff80","add":"#8fef97"},"match":"#4c66e6","cyan":"#8f9fef","uri":"#661fad","accent":"#9500ff","border":"#343036"}