{"red":"#ff3333","cyan":"#8f9fef","remaps":{"plugins":{"cmp":{"CmpItemMenu":{"fg":"#4ce659"},"CmpItemAbbrMatchFuzzy":{"fg":"#9500ff"},"CmpItemAbbrMatch":{"fg":"#9500ff"},"CmpItemAbbrDeprecated":{"fg":"#ff3333"}},"telescope":{"TelescopePromptTitle":{"bg":"#ffff80","fg":"#1a181b"},"TelescopeBorder":{"bg":"#1a181b","fg":"#1a181b"},"TelescopePreviewNormal":{"bg":"#1a181b"},"TelescopeSelectionCaret":{"bg":"#1a181b","fg":"#661fad"},"TelescopePromptNormal":{"bg":"#1a181b","fg":"#e9e2e9"},"TelescopeResultsNormal":{"bg":"#1a181b"},"TelescopePromptBorder":{"bg":"#1a181b","fg":"#e9e2e9"},"TelescopeResultsTitle":{"bg":"#4c66e6","fg":"#1a181b"},"TelescopePreviewTitle":{"bg":"#8fef97","fg":"#1a181b"},"TelescopePromptPrefix":{"fg":"#ff9933"},"TelescopeSelection":{"bg":"#343036"},"TelescopePromptCounter":{"fg":"#9500ff"},"TelescopeMatching":{"bg":"#8f9fef"}}}},"yellow":"#ffff80","orange":"#ff9933","border":"#343036","match":"#4c66e6","dimmed":{"inactive":"#343036","subtle":"#343036"},"green":"#4ce659","accent":"#9500ff","inc_search":{"bg":"#ca80ff","fg":"#f4f0f4"},"search_result":{"telescope":"#e9e2e9","bg":"#8f9fef","fg":"#e9e2e9"},"scheme-name":"kurai","pum":{"bg":"#1a181b","sel":{"fg":"#e9e2e9","bg":"#272428"},"sbar":"#272428","thumb":"#e9e2e9","fg":"#e9e2e9"},"diagnostic":{"hint":"#4c66e6","warn":"#ffff33","info":"#9500ff","error":"#ff3333"},"magenta":"#9500ff","built_in":{"constant":"#ffff80","keyword":"#ff8080","function":"#8f9fef","variable":"#ff8080"},"syntax":{"include":"#ffbf80","constructor":"#7f20df","todo":{"bg":"#aa33ff","fg":"#f4f0f4"},"string":"#ffff80","property":"#4c66e6","parameter":"#ca80ff","field":"#8f9fef","constant":"#ffff33","statement":"#ca80ff","function":"#8f9fef","variable":"#e9e2e9","conditional":"#ca80ff","type":"#8fef97","operator":"#ca80ff","comment":"#68616b","number":"#ff8080","preproc":"#ffff80","punctuation":"#68616b","struct":"#4c66e6","keyword":"#ca80ff"},"heading":{"h2":"#4ce659","h1":"#8fef97"},"uri":"#661fad","bg":{"base":"#272428","selected":"#343036","alt":"#1a181b"},"diff":{"add":"#8fef97","change":"#ffff80","delete":"#ff3333","text":"#8f9fef"},"blue":"#4c66e6","fg":"#e9e2e9"}