{"red":"#ff6188","accent":"#78dce8","magenta":"#ab9df2","dimmed":{"subtle":"#c1c0c0"},"scheme-name":"monokai_pro","bg":{"selected":"#383539","darker":"#221f22","base":"#2d2a2e"},"diagnostic":{"error":"#ff6188","warn":"#ffd866","hint":"#727072","info":"#78dce8"},"uri":"#fcfcfa","fg":"#fcfcfa","pum":{"sbar":"#4a484b","fg":"#c1c0c0","bg":"#221f22","sel":{"bg":"#727072","fg":"#ffd866"}},"orange":"#fc9867","built_in":{"function":"#78dce8","variable":"#78dce8","constant":"#78dce8","keyword":"#78dce8","type":"#78dce8"},"match":"#ffd866","heading":{"h1":"#ffd866","h2":"#ffd866"},"cyan":"#78dce8","border":"#939293","syntax":{"statement":"#ff6188","property":"#a9dc76","todo":{"fg":"#2d2a2e","bg":"#ffd866"},"preproc":"#ff6188","type":"#78dce8","variable":"#fcfcfa","constant":"#ab9df2","struct":"#78dce8","number":"#ab9df2","field":"#a9dc76","function":"#a9dc76","parameter":"#ffd866","include":"#ff6188","keyword":"#ff6188","conditional":"#ff6188","comment":"#727072","operator":"#ff6188","constructor":"#a9dc76","punctuation":"#939293","string":"#ffd866"},"inc_search":{"bg":"#ffd866","fg":"#19181a"},"yellow":"#ffd866","diff":{"text":"#78dce8","change":"#fc9867","delete":"#ff6188","add":"#a9dc76"},"search_result":{"telescope":"#fcfcfa","bg":"#727072","fg":"#fcfcfa"},"directory":"#78dce8","green":"#a9dc76","blue":"#78dce8"}