{"diagnostic":{"error":"#a67476","hint":"#b8aad9","warn":"#ccb89c","info":"#8aa387"},"cyan":"#7aacaa","dimmed":{"subtle":"#43444a","inactive":"#3c3d43"},"search_result":{"fg":"#222329","telescope":"#d4ae80","bg":"#d4ae80"},"orange":"#c8916d","syntax":{"identifier":"#b8aad9","property":"#b8aad9","struct":"#8896ae","constructor":"#9ba292","operator":"#cbc0ab","parameter":"#b8aad9","conditional":"#8896ae","field":"#d4ae80","preproc":"#d4ae80","function":"#c495a2","keyword":"#8896ae","number":"#b17f81","variable":"#cbc0ab","todo":{"bg":"#222329","fg":"#d4ae80"},"constant":"#b17f81","statement":"#b8aad9","punctuation":"#d0d0c7","comment":"#3c3d43","include":"#c495a2","string":"#8aa387"},"border":"#5a6986","blue":"#5a6986","diff":{"add":"#8aa387","change":"#ccb89c","remove":"#a67476","text":"#5a6986"},"scheme-name":"nightlamp","red":"#a67476","heading":{"h1":"#5a6986","h2":"#5a6986"},"pum":{"sbar":"#28292f","fg":"#e0d6bd","thumb":"#8d9bb3","bg":"#222329","sel":{"fg":"#cbc0ab","bg":"#8aa387"}},"directory":"#90a0a0","magenta":"#a99bca","green":"#8aa387","bg":{"selected":"#2c2d33","alt":"#15161c","base":"#18191f"},"fg":"#f1ebd1","inc_search":{"bg":"#b17f81","fg":"#222329"},"built_in":{"variable":"#9ba292","type":"#d4ae80","function":"#9ba292","keyword":"#8896ae","constant":"#b17f81"},"uri":"#b8aad9","accent":"#9ba292","match":"#e0d6bd","yellow":"#ccb89c"}