{"orange":"#c8916d","diff":{"add":"#8aa387","remove":"#a67476","text":"#5a6986","change":"#ccb89c"},"search_result":{"telescope":"#d4ae80","bg":"#d4ae80","fg":"#222329"},"blue":"#5a6986","built_in":{"constant":"#b17f81","keyword":"#8896ae","variable":"#9ba292","type":"#d4ae80","function":"#9ba292"},"scheme-name":"nightlamp","cyan":"#7aacaa","heading":{"h1":"#5a6986","h2":"#5a6986"},"syntax":{"constructor":"#9ba292","statement":"#b8aad9","keyword":"#8896ae","struct":"#8896ae","identifier":"#b8aad9","conditional":"#8896ae","include":"#c495a2","parameter":"#b8aad9","number":"#b17f81","property":"#b8aad9","variable":"#cbc0ab","string":"#8aa387","constant":"#b17f81","field":"#d4ae80","comment":"#3c3d43","operator":"#cbc0ab","preproc":"#d4ae80","punctuation":"#d0d0c7","todo":{"bg":"#222329","fg":"#d4ae80"},"function":"#c495a2"},"green":"#8aa387","match":"#e0d6bd","bg":{"base":"#18191f","selected":"#2c2d33","alt":"#15161c"},"diagnostic":{"warn":"#ccb89c","info":"#8aa387","error":"#a67476","hint":"#b8aad9"},"border":"#5a6986","red":"#a67476","fg":"#f1ebd1","inc_search":{"bg":"#b17f81","fg":"#222329"},"uri":"#b8aad9","pum":{"sel":{"fg":"#cbc0ab","bg":"#8aa387"},"bg":"#222329","sbar":"#28292f","thumb":"#8d9bb3","fg":"#e0d6bd"},"dimmed":{"inactive":"#3c3d43","subtle":"#43444a"},"yellow":"#ccb89c","accent":"#9ba292","magenta":"#a99bca","directory":"#90a0a0"}