{"accent":"#9ba292","blue":"#5a6986","heading":{"h1":"#5a6986","h2":"#5a6986"},"directory":"#90a0a0","diff":{"remove":"#a67476","change":"#ccb89c","add":"#8aa387","text":"#5a6986"},"yellow":"#ccb89c","scheme-name":"nightlamp","cyan":"#7aacaa","diagnostic":{"hint":"#b8aad9","error":"#a67476","warn":"#ccb89c","info":"#8aa387"},"orange":"#c8916d","red":"#a67476","pum":{"bg":"#222329","fg":"#e0d6bd","sbar":"#28292f","thumb":"#8d9bb3","sel":{"bg":"#8aa387","fg":"#cbc0ab"}},"fg":"#f1ebd1","match":"#e0d6bd","search_result":{"fg":"#222329","telescope":"#d4ae80","bg":"#d4ae80"},"border":"#5a6986","dimmed":{"subtle":"#43444a","inactive":"#3c3d43"},"inc_search":{"fg":"#222329","bg":"#b17f81"},"built_in":{"type":"#d4ae80","keyword":"#8896ae","variable":"#9ba292","function":"#9ba292","constant":"#b17f81"},"syntax":{"punctuation":"#d0d0c7","identifier":"#b8aad9","variable":"#cbc0ab","statement":"#b8aad9","constructor":"#9ba292","operator":"#cbc0ab","parameter":"#b8aad9","comment":"#3c3d43","conditional":"#8896ae","number":"#b17f81","function":"#c495a2","todo":{"fg":"#d4ae80","bg":"#222329"},"property":"#b8aad9","constant":"#b17f81","keyword":"#8896ae","field":"#d4ae80","preproc":"#d4ae80","string":"#8aa387","struct":"#8896ae","include":"#c495a2"},"bg":{"alt":"#15161c","selected":"#2c2d33","base":"#18191f"},"magenta":"#a99bca","uri":"#b8aad9","green":"#8aa387"}