{"cyan":"#4EC9B0","orange":"#d08770","green":"#98C379","match":"#E5E9F0","diagnostic":{"hint":"#5d8ac2","info":"#d94848","error":"#d94848","warn":"#d4d198"},"built_in":{"function":"#d4d198","variable":"#8fc6e3","type":"#d4d198","constant":"#5d8ac2","keyword":"#5d8ac2"},"search_result":{"fg":"#c487b9","telescope":"#5d8ac2","bg":"#2e3440"},"blue":"#5d8ac2","red":"#d94848","syntax":{"property":"#d4d198","variable":"#d94848","include":"#d94848","constructor":"#84D9AA","number":"#B4CDA8","constant":"#5d8ac2","punctuation":"#5d8ac2","preproc":"#d94848","function":"#5d8ac2","keyword":"#5d8ac2","type":"#d94848","parameter":"#8fc6e3","string":"#A3BE8C","struct":"#d94848","todo":{"fg":"#2e3440","bg":"#d4d198"},"comment":"#699856","operator":"#5d8ac2","field":"#8fc6e3"},"magenta":"#c487b9","scheme-name":"papa_dark","border":"#5d8ac2","bg":{"alt":"#2b2e36","selected":"#3B4252","base":"#2e3440"},"diff":{"add":"#98C379","change":"#d4d198","remove":"#d94848","text":"#5d8ac2"},"remaps":{"langs":{"md":{"markdownCode":{"fg":"#A3BE8C"}}},"plugins":{"telescope":{"TelescopePromptTitle":{"fg":"#2b2e36","bg":"#d4d198"},"TelescopeResultsNormal":{"bg":"#2b2e36"},"TelescopeBorder":{"fg":"#2b2e36","bg":"#2b2e36"},"TelescopePromptPrefix":{"fg":"#5d8ac2","bg":"#2b2e36"},"TelescopePreviewNormal":{"bg":"#2b2e36"},"TelescopeSelectionCaret":{"fg":"#2b2e36","bg":"#2b2e36"},"TelescopePromptBorder":{"fg":"#2e3440","bg":"#2b2e36"},"TelescopePromptNormal":{"fg":"#E5E9F0","bg":"#2b2e36"},"TelescopePreviewTitle":{"fg":"#2b2e36","bg":"#98C379"},"TelescopeResultsTitle":{"fg":"#2b2e36","bg":"#5d8ac2"},"TelescopeMatching":{"fg":"#5d8ac2"},"TelescopeSelection":{"bg":"#434c5e"}},"lsp":{"DiagnosticUnderlineHint":{"fg":"NONE","sp":"#8fc6e3","style":"underline"},"DiagnosticUnderlineWarn":{"fg":"NONE","sp":"#d4d198","style":"underline"}},"trouble":{"TroubleSignError":{"fg":"#d94848"},"TroubleSignWarning":{"fg":"#d4d198"}},"gitsigns":{"GitSignsDelete":{"fg":"#d94848"},"GitSignsChange":{"fg":"#d4d198","bg":"#2e3440"}},"treesitter":{"TSFunction":{"link":"Function"},"@constant.builtin":{"link":"Keyword"},"@variable":{"link":"TSField"},"TSBoolean":{"link":"Boolean"},"@punctuation.bracket":{"fg":"#5d8ac2"},"@error":{"link":"Error"},"TSConditional":{"link":"Keyword"},"@type":{"fg":"#4EC9B0"},"@keyword":{"fg":"#5d8ac2"},"@property":{"link":"TSField"},"TSProperty":{"link":"TSField"},"TSVariable":{"link":"TSField"},"@text.title":{"link":"String"},"TSConstBuiltin":{"link":"Keyword"},"@field":{"fg":"#8fc6e3"},"TSFuncMacro":{"link":"Function"},"@boolean":{"link":"Boolean"},"@function":{"link":"Function"},"TSVariableBuiltin":{"link":"Keyword"},"TSLabel":{"link":"String"},"@label":{"link":"String"},"TSFuncBuiltin":{"link":"Function"},"TSField":{"fg":"#8fc6e3"},"TSTitle":{"link":"String"},"@constructor":{"fg":"#5d8ac2"},"TSTag":{"link":"Keyword"},"@character":{"link":"Character"},"@tag":{"link":"Keyword"},"@variable.builtin":{"link":"Keyword"},"TSInclude":{"link":"Keyword"},"@include":{"link":"Keyword"},"@constant":{"link":"Constant"},"@type.builtin":{"fg":"#5d8ac2"},"@conditional":{"link":"Keyword"},"@function.macro":{"link":"Function"},"TSMethod":{"link":"Function"},"@keyword.function":{"link":"Keyword"},"TSError":{"link":"Error"},"TSKeywordFunction":{"link":"Keyword"},"@method":{"link":"Function"},"TSConstructor":{"fg":"#5d8ac2"},"@function.builtin":{"link":"Function"},"TSPunctBracket":{"fg":"#5d8ac2"},"TSKeyword":{"fg":"#5d8ac2"},"TSTypeBuiltin":{"fg":"#5d8ac2"},"TSCharacter":{"link":"Character"},"TSNamespace":{"fg":"#4EC9B0"},"TSConstant":{"link":"Constant"},"@namespace":{"fg":"#4EC9B0"},"TSType":{"fg":"#4EC9B0"}},"cmp":{"CmpItemMenu":{"fg":"#5d8ac2"},"CmpItemKind":{"fg":"#5d8ac2"},"CmpItemAbbrMatch":{"fg":"#8fc6e3"},"CmpItemAbbr":{"fg":"#E5E9F0"},"CmpItemKindVariable":{"fg":"#8fc6e3"}},"nvim_tree":{"NvimTreeGitDeleted":{"fg":"#d94848"},"NvimTreeRootFolder":{"fg":"#8fc6e3"},"NvimTreeFileDeleted":{"fg":"#d94848"},"NvimTreeGitDirty":{"fg":"#d4d198"}}},"base":{"VertSplit":{"fg":"#373e4a","bg":"#2e3440"},"Normal":{"fg":"#E5E9F0","bg":"#2e3440"},"Identifier":{"fg":"#8fc6e3"},"TabLine":{"fg":"#699856"},"Folded":{"fg":"#699856"},"FloatBorder":{"fg":"#E5E9F0"},"NonText":{"fg":"#5d8ac2"},"Statement":{"fg":"#5d8ac2"},"Character":{"link":"String"},"Number":{"fg":"#B4CDA8"},"ColorColumn":{"fg":"#d94848"},"CursorLine":{"bg":"#3B4252"},"Special":{"fg":"#5d8ac2"},"Float":{"link":"Number"},"Boolean":{"link":"Constant"},"Function":{"fg":"#d4d198"},"Constant":{"fg":"#5d8ac2"},"WarningMsg":{"fg":"#d4d198"},"Type":{"fg":"#5d8ac2"},"Whitespace":{"fg":"#E5E9F0"},"Visual":{"bg":"#3E4452"},"TabLineFill":{"bg":"#2e3440"},"TabLineSel":{"fg":"#E5E9F0"},"Search":{"bg":"#5d8ac2"},"PreProc":{"link":"Statement"},"EndOfBuffer":{"fg":"#2e3440"},"ErrorMsg":{"fg":"#E5E9F0","bg":"#d94848"},"CursorLineNr":{"fg":"#E5E9F0"},"MatchParen":{"fg":"#E5E9F0","bg":"#5d8ac2"},"IncSearch":{"fg":"#d4d198","bg":"#699856"},"Directory":{"fg":"#5d8ac2"}}},"yellow":"#d4d198","heading":{"h2":"#d94848","h1":"#d94848"},"pum":{"bg":"#2e3440","sbar":"#3E4452","fg":"#3B4252","sel":{"bg":"#3E4452"},"thumb":"#E5E9F0"},"uri":"#d94848","dimmed":{"subtle":"#4c566a","inactive":"#4C566A"},"accent":"#5d8ac2"}