{"uri":"#c4a7e7","built_in":{"function":"#eb6f92","constant":"#eb6f92","variable":"#eb6f92","type":"#9ccfd8","keyword":"#31748f"},"diff":{"text":"#826a6f","remove":"#82435b","change":"#26233a","add":"#5b737e"},"green":"#31748f","cyan":"#ebbcba","dimmed":{"inactive":"#6e6a86","subtle":"#6e6a86"},"heading":{"h1":"#c4a7e7","h2":"#0"},"search_result":{"fg":"#0","telescope":"#ebbcba","bg":"#403d52"},"accent":"#ebbcba","blue":"#9ccfd8","gitsigns":{"remove":"#eb6f92","change":"#ebbcba","add":"#9ccfd8"},"scheme-name":"rose_pine","fg":"#e0def4","match":"#e0def4","inc_search":{"fg":"#191724","bg":"#ebbcba"},"bg":{"alt":"#1f1d2e","base":"#191724","selected":"#21202e"},"orange":"#f6c177","magenta":"#c4a7e7","syntax":{"punctuation":"#6e6a86","field":"#9ccfd8","include":"#c4a7e7","operator":"#908caa","function":"#ebbcba","variable":"#e0def4","preproc":"#c4a7e7","struct":"#9ccfd8","statement":"#31748f","keyword":"#31748f","number":"#f6c177","constructor":"#9ccfd8","constant":"#9ccfd8","tag":"#9ccfd8","conditional":"#31748f","string":"#f6c177","type":"#9ccfd8","todo":{"fg":"#c4a7e7","bg":"#0"},"property":"#c4a7e7","parameter":"#c4a7e7","comment":"#6e6a86"},"yellow":"#f6c177","cursorlinenr":"#e0def4","border":"#403d52","diagnostic":{"info":"#9ccfd8","warn":"#f6c177","hint":"#c4a7e7","error":"#eb6f92"},"pum":{"sel":{"fg":"#e0def4","bg":"#26233a"},"fg":"#908caa","sbar":"#21202e","thumb":"#403d52","bg":"#1f1d2e"}}