{"accent":"#ea9a97","blue":"#9ccfd8","heading":{"h1":"#c4a7e7","h2":"#0"},"diff":{"text":"#875e67","change":"#393552","add":"#607887","remove":"#874864"},"yellow":"#f6c177","cursorlinenr":"#e0def4","cyan":"#ea9a97","diagnostic":{"hint":"#c4a7e7","error":"#eb6f92","info":"#9ccfd8","warn":"#f6c177"},"orange":"#f6c177","scheme-name":"rose_pine_moon","match":"#e0def4","fg":"#e0def4","built_in":{"type":"#7aa89f","keyword":"#957fb8","variable":"#eb6f92","constant":"#eb6f92","function":"#eb6f92"},"dimmed":{"subtle":"#817c9c","inactive":"#59546d"},"border":"#817c9c","green":"#3e8fb0","search_result":{"fg":"#c4a7e7","bg":"#56526e","telescope":"#dcd7ba"},"pum":{"sel":{"fg":"#e0def4","bg":"#393552"},"fg":"#817c9c","sbar":"#393552","thumb":"#59546d","bg":"#2a273f"},"bg":{"selected":"#2a283e","alt":"#2a273f","base":"#232136"},"inc_search":{"fg":"#0","bg":"#44415a"},"magenta":"#c4a7e7","uri":"#f6c177","syntax":{"type":"#7aa89f","punctuation":"#817c9c","preproc":"#c4a7e7","variable":"#e0def4","statement":"#3e8fb0","constructor":"#9ccfd8","operator":"#817c9c","parameter":"#c4a7e7","comment":"#817c9c","conditional":"#957fb8","constant":"#9ccfd8","number":"#f6c177","tag":"#9ccfd8","property":"#c4a7e7","struct":"#9ccfd8","keyword":"#3e8fb0","field":"#9ccfd8","todo":{"fg":"#c4a7e7","bg":"#0"},"function":"#ea9a97","include":"#c4a7e7","string":"#f6c177"}}