{"yellow":"#f6c177","dimmed":{"inactive":"#555169","subtle":"#6e6a86"},"pum":{"fg":"#6e6a86","sel":{"fg":"#e0def4","bg":"#26233a"},"bg":"#1e1e2e","thumb":"#555169","sbar":"#26233a"},"uri":"#f6c177","magenta":"#c4a7e7","green":"#9ccfd8","blue":"#3e8fb0","built_in":{"function":"#ff789e","keyword":"#3e8fb0","type":"#9ccfd8","constant":"#ff789e","variable":"#ff789e"},"search_result":{"fg":"#12121e","bg":"#ebbcba","telescope":"#ebbcba"},"scheme-name":"sakura","cursorlinenr":"#6ea86","orange":"#f6c177","heading":{"h1":"#ebbcba","h2":"#0"},"diagnostic":{"info":"#9ccfd8","hint":"#c4a7e7","error":"#ff789e","warn":"#f6c177"},"border":"#6e6a86","accent":"#ebbcba","cyan":"#ebbcba","syntax":{"statement":"#3e8fb0","keyword":"#3e8fb0","field":"#9ccfd8","tag":"#9ccfd8","parameter":"#c4a7e7","include":"#c4a7e7","preproc":"#c4a7e7","constant":"#9ccfd8","todo":{"bg":"#0","fg":"#c4a7e7"},"operator":"#3e8fb0","constructor":"#9ccfd8","conditional":"#3e8fb0","variable":"#e0def4","function":"#ebbcba","punctuation":"#6e6a86","struct":"#9ccfd8","type":"#9ccfd8","property":"#c4a7e7","comment":"#555169","string":"#f6c177","number":"#f6c177"},"match":"#ebbcba","inc_search":{"fg":"#12121e","bg":"#ff789e"},"bg":{"base":"#12121e","selected":"#211f2d","alt":"#1e1e2e"},"diff":{"add":"#0","change":"#0","remove":"#0","text":"#0"},"fg":"#e0def4"}