{"fg":"#fce8c3","scheme-name":"scery","bg":{"alt":"#303030","base":"#1c1b19","selected":"#303030"},"built_in":{"constant":"#aaeb3","variable":"#aaeb3","function":"#fbb829","keyword":"#ef2f27","type":"#68a8e4"},"border":"#fce8c3","orange":"#FED06E","cyan":"#0AAEB3","diagnostic":{"info":"#add8e6","error":"#ff0000","hint":"#d3d3d3","warn":"#ffa500"},"inc_search":{"bg":"#4e4e4e","fg":"#0"},"search_result":{"fg":"#0","telescope":"#e02c6d","bg":"#4e4e4e"},"yellow":"#FBB829","green":"#519F50","pum":{"fg":"#fce8c3","sbar":"#1c1b19","sel":{"bg":"#2c78bf","fg":"#fce8c3"},"bg":"#303030","thumb":"#1c1b19"},"cursorlinenr":"#fbb829","magenta":"#E02C6D","blue":"#2C78BF","heading":{"h2":"#0","h1":"#0"},"accent":"#ff5f00","diff":{"add":"#1c1b19","change":"#1c1b19","text":"#1c1b19","remove":"#1c1b19"},"dimmed":{"subtle":"#918175","inactive":"#444444"},"uri":"#519f50","syntax":{"constructor":"#ff5f00","parameter":"#aaeb3","operator":"#fce8c3","preproc":"#aaeb3","struct":"#aaeb3","variable":"#fce8c3","comment":"#918175","conditional":"#ef2f27","tag":"#2c78bf","type":"#baa67f","function":"#fbb829","punctuation":"#918175","field":"#519f50","number":"#ff5c8f","include":"#aaeb3","string":"#98bc37","keyword":"#ef2f27","todo":{"fg":"#fce8c3","bg":"#1c1b19"},"property":"#68a8e4","statement":"#ef2f27","constant":"#ff5c8f"},"match":"#0"}