{"magenta":"#E02C6D","border":"#fce8c3","yellow":"#FBB829","inc_search":{"fg":"#0","bg":"#4e4e4e"},"match":"#0","heading":{"h1":"#0","h2":"#0"},"scheme-name":"scery","cyan":"#0AAEB3","blue":"#2C78BF","cursorlinenr":"#fbb829","search_result":{"bg":"#4e4e4e","telescope":"#e02c6d","fg":"#0"},"built_in":{"type":"#68a8e4","function":"#fbb829","variable":"#aaeb3","keyword":"#ef2f27","constant":"#aaeb3"},"diagnostic":{"hint":"#d3d3d3","info":"#add8e6","warn":"#ffa500","error":"#ff0000"},"green":"#519F50","dimmed":{"subtle":"#918175","inactive":"#444444"},"accent":"#ff5f00","uri":"#519f50","orange":"#FED06E","bg":{"base":"#1c1b19","alt":"#303030","selected":"#303030"},"diff":{"change":"#1c1b19","remove":"#1c1b19","add":"#1c1b19","text":"#1c1b19"},"syntax":{"string":"#98bc37","field":"#519f50","statement":"#ef2f27","comment":"#918175","variable":"#fce8c3","punctuation":"#918175","constructor":"#ff5f00","preproc":"#aaeb3","keyword":"#ef2f27","type":"#baa67f","include":"#aaeb3","constant":"#ff5c8f","todo":{"bg":"#1c1b19","fg":"#fce8c3"},"struct":"#aaeb3","operator":"#fce8c3","conditional":"#ef2f27","function":"#fbb829","tag":"#2c78bf","number":"#ff5c8f","parameter":"#aaeb3","property":"#68a8e4"},"pum":{"sel":{"fg":"#fce8c3","bg":"#2c78bf"},"bg":"#303030","thumb":"#1c1b19","sbar":"#1c1b19","fg":"#fce8c3"},"fg":"#fce8c3"}