{"blue":"#76cce0","heading":{"h1":"#fc5d7c","h2":"#0"},"diff":{"remove":"#55393d","change":"#354157","add":"#394634","text":"#76cce0"},"diagnostic":{"error":"#fc5d7c","warn":"#e7c664","info":"#85d3f2","hint":"#e2e2e3"},"scheme-name":"sonokai_deep","bg":{"base":"#161C23","alt":"#161C23","selected":"#1E2A35"},"remaps":{"base":{"Directory":{"fg":"#76cce0"},"EndOfBuffer":{"fg":"#161C23"},"ErrorMsg":{"bg":"#fc5d7c","fg":"#e2e2e3"},"ColorColumn":{"bg":"#1E2A35"},"Normal":{"bg":"#161C23","fg":"#e2e2e3"},"VertSplit":{"bg":"#161C23","fg":"#7f8490"}},"plugins":{"lsp":{"DiagnosticVirtualTextHint":{"style":"italic","fg":"#414550"},"DiagnosticVirtualTextWarn":{"style":"italic","fg":"#414550"},"DiagnosticVirtualTextInfo":{"style":"italic","fg":"#414550"},"DiagnosticUnderlineError":{"style":"undercurl","fg":"#0"},"DiagnosticUnderlineWarn":{"style":"undercurl","fg":"#0"},"DiagnosticUnderlineInfo":{"style":"undercurl","fg":"#0"},"DiagnosticUnderlineHint":{"style":"undercurl","fg":"#0"},"DiagnosticVirtualTextError":{"style":"italic","fg":"#414550"}},"cmp":{"CmpItemMenu":{"fg":"#76cce0"}},"treesitter":{"@symbol":{"link":"ThemerType"}},"telescope":{"TelescopeTitle":{"bg":"#161C23","fg":"#76cce0"},"TelescopeSelectionCaret":{"bg":"#161C23","fg":"#e7c664"},"TelescopePromptPrefix":{"fg":"#e7c664"},"TelescopeMatching":{"fg":"#e7c664"},"TelescopePromptCounter":{"fg":"#e7c664"}}}},"syntax":{"include":"#fc5d7c","operator":"#b39df3","struct":"#76cce0","type":"#76cce0","keyword":"#fc5d7c","comment":"#7f8490","field":"#76cce0","property":"#e2e2e3","preproc":"#fc5d7c","parameter":"#e2e2e3","variable":"#e2e2e3","conditional":"#f39660","statement":"#fc5d7c","function":"#9ed072","constant":"#f39660","todo":{"fg":"#76cce0","bg":"#0"},"number":"#b39df3","punctuation":"#7f8490","string":"#e7c664","constructor":"#9ed072","tag":"#76cce0"},"built_in":{"function":"#9ed072","constant":"#f39660","type":"#76cce0","keyword":"#fc5d7c","variable":"#e2e2e3"},"fg":"#e2e2e3","pum":{"bg":"#161C23","sbar":"#161C23","sel":{"fg":"#161C23","bg":"#85d3f2"},"thumb":"#7f8490","fg":"#e2e2e3"},"red":"#fc5d7c","match":"#a7df78","gitsigns":{"remove":"#fc5d7c","add":"#9ed072","change":"#76cce0"},"search_result":{"telescope":"#a7df78","fg":"#161C23","bg":"#a7df78"},"yellow":"#e7c664","inc_search":{"bg":"#161C23","fg":"#fc5d7c"},"cursorlinenr":"#e2e2e3","orange":"#f39660","green":"#9ed072","uri":"#76cce0","magenta":"#b39df3","dimmed":{"subtle":"#7f8490","inactive":"#414550"},"accent":"#b39df3","border":"#7f8490","cyan":"#354157"}