{"cyan":"#38a89d","built_in":{"function":"#a485dd","variable":"#a485dd","constant":"#a485dd","keyword":"#ee6d85","type":"#7199ee"},"dimmed":{"subtle":"#4a5057","inactive":"#4a5057"},"bg":{"selected":"#1a1b2a","alt":"#11121d","base":"#11121d"},"heading":{"h2":"#0","h1":"#0"},"accent":"#a485dd","diagnostic":{"info":"#add8e6","hint":"#d3d3d3","warn":"#ffa500","error":"#ff0000"},"blue":"#7199ee","green":"#95c561","cursorlinenr":"#a0a8cd","match":"#7199ee","border":"#282c34","uri":"#80a0ff","yellow":"#d7a65f","syntax":{"statement":"#ee6d85","parameter":"#f6955b","string":"#d7a65f","todo":{"fg":"#7199ee","bg":"#0"},"comment":"#4a5057","number":"#a485dd","keyword":"#ee6d85","variable":"#0","operator":"#ee6d85","constant":"#f6955b","function":"#95c561","field":"#f6955b","conditional":"#ee6d85","property":"#f6955b","tag":"#a485dd","constructor":"#a485dd","preproc":"#ee6d85","punctuation":"#a0a8cd","struct":"#7199ee","include":"#ee6d85","type":"#7199ee"},"pum":{"bg":"#11121d","sbar":"#11121d","sel":{"fg":"#11121d","bg":"#98c379"},"thumb":"#212234","fg":"#a0a8cd"},"magenta":"#a485dd","search_result":{"bg":"#98c379","telescope":"#0","fg":"#11121d"},"diff":{"remove":"#281b27","add":"#1e2326","change":"#262b3d","text":"#0"},"inc_search":{"fg":"#11121d","bg":"#fe6d85"},"scheme-name":"tokyodark","fg":"#a0a8cd","orange":"#d7a65f"}