{"diff":{"text":"#394b70","change":"#272D43","add":"#283B4D","remove":"#3F2D3D"},"accent":"#2ac3de","cyan":"#7dcfff","scheme-name":"tokyonight","red":"#f7768e","orange":"#ff9e64","heading":{"h1":"#bb9af7","h2":"#7aa2f7"},"diagnostic":{"hint":"#1abc9c","info":"#0db9d7","warn":"#e0af68","error":"#db4b4b"},"inc_search":{"fg":"#1D202F","bg":"#ff9e64"},"fg":"#c0caf5","uri":"#c0caf5","search_result":{"bg":"#3d59a1","telescope":"#c0caf5","fg":"#c0caf5"},"dimmed":{"subtle":"#a9b1d6","linenr":"#3b4261","inactive":"#545c7e"},"built_in":{"keyword":"#bb9af7","function":"#2ac3de","type":"#2ac3de","constant":"#2ac3de","variable":"#f7768e"},"match":"#2ac3de","pum":{"fg":"#c0caf5","sel":{"fg":"#c0caf5","bg":"#343A55"},"bg":"#1f2335","sbar":"#222229","thumb":"#3b4261"},"syntax":{"string":"#9ece6a","preproc":"#7dcfff","keyword":"#bb9af7","struct":"#ff9e64","parameter":"#e0af68","statement":"#bb9af7","constant":"#ff9e64","function":"#7aa2f7","operator":"#89ddff","todo":{"bg":"#e0af68","fg":"#1a1b26"},"conditional":"#bb9af7","punctuation":"#a9b1d6","property":"#73daca","field":"#73daca","number":"#ff9e64","constructor":"#bb9af7","type":"#2ac3de","comment":"#565f89","include":"#7dcfff","variable":"#c0caf5"},"border":"#1D202F","magenta":"#bb9af7","bg":{"base":"#1a1b26","alt":"#24283b","selected":"#292e42"},"green":"#9ece6a","directory":"#7aa2f7","blue":"#7aa2f7","yellow":"#e0af68"}