{"built_in":{"variable":"#53a7bf","type":"#e59e67","keyword":"#53a7bf","constant":"#53a7bf","function":"#6db0ad"},"heading":{"h1":"#0","h2":"#0"},"dimmed":{"inactive":"#b185db","subtle":"#c5c8c9"},"fg":"#c5c8c9","orange":"#e7c787","green":"#A3BE8C","yellow":"#e7c787","cyan":"#519ABA","accent":"#53a7bf","cursorlinenr":"#c4c4c4","scheme-name":"uwu","match":"#0","blue":"#61afef","diagnostic":{"hint":"#d3d3d3","warn":"#ffa500","info":"#add8e6","error":"#ff0000"},"diff":{"add":"#131a1c","remove":"#131a1c","text":"#131a1c","change":"#131a1c"},"syntax":{"punctuation":"#c4c4c4","number":"#51a39f","conditional":"#f65b5b","keyword":"#b185db","tag":"#53a7bf","property":"#f65b5b","todo":{"fg":"#b185db","bg":"#ffff00"},"type":"#e59e67","operator":"#53a7bf","constructor":"#53a7bf","comment":"#2f3638","parameter":"#f65b5b","struct":"#e59e67","constant":"#51a39f","field":"#f65b5b","preproc":"#53a7bf","variable":"#53a7bf","function":"#f65b5b","include":"#f65b5b","string":"#6bb05d","statement":"#e59e67"},"border":"#1b2224","uri":"#e59e67","pum":{"fg":"#c4c4c4","thumb":"#ffffff","sbar":"#808080","bg":"#1b2224","sel":{"bg":"#b185db","fg":"#2f3638"}},"inc_search":{"bg":"#0","fg":"#e59e67"},"search_result":{"bg":"#2f3638","telescope":"#53a7bf","fg":"#53a7bf"},"bg":{"alt":"#1b2224","base":"#131a1c","selected":"#1b2224"},"magenta":"#c882e7"}