{"heading":{"h2":"#0","h1":"#0"},"border":"#1b2224","match":"#0","search_result":{"fg":"#53a7bf","telescope":"#53a7bf","bg":"#2f3638"},"magenta":"#c882e7","orange":"#e7c787","green":"#A3BE8C","accent":"#53a7bf","dimmed":{"subtle":"#c5c8c9","inactive":"#b185db"},"diff":{"remove":"#131a1c","change":"#131a1c","text":"#131a1c","add":"#131a1c"},"blue":"#61afef","bg":{"selected":"#1b2224","alt":"#1b2224","base":"#131a1c"},"cyan":"#519ABA","scheme-name":"uwu","syntax":{"function":"#f65b5b","preproc":"#53a7bf","variable":"#53a7bf","conditional":"#f65b5b","keyword":"#b185db","operator":"#53a7bf","comment":"#2f3638","number":"#51a39f","todo":{"fg":"#b185db","bg":"#ffff00"},"field":"#f65b5b","string":"#6bb05d","include":"#f65b5b","statement":"#e59e67","punctuation":"#c4c4c4","type":"#e59e67","property":"#f65b5b","parameter":"#f65b5b","constructor":"#53a7bf","tag":"#53a7bf","struct":"#e59e67","constant":"#51a39f"},"fg":"#c5c8c9","cursorlinenr":"#c4c4c4","uri":"#e59e67","pum":{"fg":"#c4c4c4","sbar":"#808080","bg":"#1b2224","thumb":"#ffffff","sel":{"bg":"#b185db","fg":"#2f3638"}},"diagnostic":{"error":"#ff0000","info":"#add8e6","hint":"#d3d3d3","warn":"#ffa500"},"inc_search":{"bg":"#0","fg":"#e59e67"},"built_in":{"function":"#6db0ad","type":"#e59e67","variable":"#53a7bf","keyword":"#53a7bf","constant":"#53a7bf"},"yellow":"#e7c787"}